pixel_collect/__init__.py
pixel_collect/main.py
pixel_collect-0.0.1.dist-info/METADATA
pixel_collect-0.0.1.dist-info/WHEEL
pixel_collect-0.0.1.dist-info/top_level.txt
pixel_collect-0.0.1.dist-info/RECORD
